genealloy/GeneAlloy.py
genealloy/__init__.py
genealloy/codontable.py
genealloy-0.1.2.dist-info/licenses/LICENSE
tests/test_codontable.py
tests/test_genealloy.py
genealloy-0.1.2.dist-info/METADATA
genealloy-0.1.2.dist-info/WHEEL
genealloy-0.1.2.dist-info/top_level.txt
genealloy-0.1.2.dist-info/RECORD
