Metadata-Version: 2.4
Name: genealloy
Version: 0.1.2
Summary: GeneAlloy helps designing overlapping sequences.
Author: Peter Vegh
License-Expression: MIT
Project-URL: Homepage, https://github.com/Edinburgh-Genome-Foundry/GeneAlloy/
Keywords: biology
License-File: LICENSE
Requires-Dist: biopython
Dynamic: license-file
